portal_gun/__init__.py
portal_gun/__main__.py
portal_gun/main.py
portal_gun/aws/__init__.py
portal_gun/aws/aws_client.py
portal_gun/aws/exceptions.py
portal_gun/aws/helpers.py
portal_gun/commands/__init__.py
portal_gun/commands/base_command.py
portal_gun/commands/close_portal.py
portal_gun/commands/common.py
portal_gun/commands/exceptions.py
portal_gun/commands/generate_portal_spec.py
portal_gun/commands/open_channel.py
portal_gun/commands/open_portal.py
portal_gun/commands/show_portal_info.py
portal_gun/commands/ssh.py
portal_gun/commands/volume.py
portal_gun/configuration/__init__.py
portal_gun/configuration/constants.py
portal_gun/configuration/helpers.py
portal_gun/configuration/schemas/__init__.py
portal_gun/configuration/schemas/config.py
portal_gun/configuration/schemas/portal.py
portal_gun/context_managers/__init__.py
portal_gun/context_managers/no_print.py
portal_gun/context_managers/print_indent.py
portal_gun/context_managers/print_scope.py
portal_gun/context_managers/step.py
portal_gun/helpers/__init__.py
portal_gun/helpers/pretty_print.py
portal_gun-0.2.0.dist-info/LICENSE.txt
portal_gun-0.2.0.dist-info/METADATA
portal_gun-0.2.0.dist-info/RECORD
portal_gun-0.2.0.dist-info/WHEEL
portal_gun-0.2.0.dist-info/entry_points.txt
portal_gun-0.2.0.dist-info/top_level.txt
