Metadata-Version: 2.1
Name: portal-gun
Version: 0.2.0
Summary: A command line tool that automates repetitive tasks associated with the management of Spot Instances on Amazon EC2 service.
Home-page: https://github.com/Coderik/portal-gun
Author: Vadim Fedorov
Author-email: coderiks@gmail.com
License: MIT
Project-URL: Source, https://github.com/Coderik/portal-gun
Project-URL: Bug Reports, https://github.com/Coderik/portal-gun/issues
Platform: UNKNOWN
Classifier: Development Status :: 4 - Beta
Classifier: Environment :: Console
Classifier: Intended Audience :: Science/Research
Classifier: Topic :: Scientific/Engineering :: Artificial Intelligence
Classifier: License :: OSI Approved :: MIT License
Classifier: Programming Language :: Python :: 2
Classifier: Programming Language :: Python :: 2.7
Requires-Dist: boto3 (>=1.5.18)
Requires-Dist: Fabric (>=1.14.0)
Requires-Dist: marshmallow (>=3.0.0b8)
